inovopy/__init__.py
inovopy/rosbridge.py
inovopy/util.py
inovopy/geometry/__init__.py
inovopy/geometry/jointcoord.py
inovopy/geometry/transform.py
inovopy/iva/__init__.py
inovopy/robot/__init__.py
inovopy/socket/__init__.py
inovopy/socket/tcp_listener.py
inovopy/socket/tcp_stream.py
inovopy-1.0.1.dist-info/METADATA
inovopy-1.0.1.dist-info/WHEEL
inovopy-1.0.1.dist-info/top_level.txt
inovopy-1.0.1.dist-info/RECORD
