Metadata-Version: 2.4
Name: inovopy
Version: 1.0.1
Summary: Inovo Robot Arm API
Author: Alan Chung
Author-email: deeralan827@gmail.com
Keywords: python,robotics,inovo robotics,inovo robot arm,motion,sockets
Classifier: Development Status :: 1 - Planning
Classifier: Intended Audience :: Developers
Classifier: Programming Language :: Python :: 3
Classifier: Operating System :: Unix
Classifier: Operating System :: MacOS :: MacOS X
Classifier: Operating System :: Microsoft :: Windows
Requires-Dist: numpy
Requires-Dist: roslibpy
Dynamic: author
Dynamic: author-email
Dynamic: classifier
Dynamic: description
Dynamic: description-content-type
Dynamic: keywords
Dynamic: requires-dist
Dynamic: summary
